{"room_id": "0b76833fa27749bebde9f5af201cfcaf", "config_filename": "/Users/jgrizou/workspace/openvault_web/server/configs/level_6_visible_nocheck.json", "config": {"name": "Level 6 - Visible - No Check", "code": {"secret_code": [0, 0, 0, 0], "show_code": true, "check_code": false}, "learner": {"type": "continuous", "n_hypothesis": 10, "accumulate_info_between_numbers": true}, "pad": {"type": "draw", "show_learning_progress": true}}, "client_ip": "127.0.0.1", "client_ip_info": {"message": "reserved range", "query": "127.0.0.1", "status": "fail"}, "user_agent": "Mozilla/5.0 (Macintosh; Intel Mac OS X 10_14_5) AppleWebKit/537.36 (KHTML, like Gecko) Chrome/74.0.3729.169 Safari/537.36", "user_platform": "macos", "user_browser": "chrome", "timestamp": 1560444472.175104, "timestamp_human_readable": "18:47:52 on 13/06/2019"}